{"lastUsed":1632851648953,"path":"C:\/Users\/blanc\/OneDrive\/Documentos\/1er Curso\/2º Cuatrimestre\/MP\/Lab\/Sesión 11\/ws11","projectCount":4,"recentFiles":[{"path":"\/lab12_exam_marker_initial\/src\/uo\/mp\/lab12\/serializers","parentWorkspace":"C:\/Users\/blanc\/OneDrive\/Documentos\/1er Curso\/2º Cuatrimestre\/MP\/Lab\/Sesión 11\/ws11","name":"MarkSerializer.java","lastModified":1619262034000},{"path":"\/eduardo_blanco_bielsa_session11_task_newsstand\/src\/uo\/mp\/newsstand\/domain","parentWorkspace":"C:\/Users\/blanc\/OneDrive\/Documentos\/1er Curso\/2º Cuatrimestre\/MP\/Lab\/Sesión 11\/ws11","name":"Magazine.java","lastModified":1618649066000},{"path":"\/lab12_exam_marker_initial\/src\/uo\/mp\/lab12\/marks","parentWorkspace":"C:\/Users\/blanc\/OneDrive\/Documentos\/1er Curso\/2º Cuatrimestre\/MP\/Lab\/Sesión 11\/ws11","name":"StudentMark.java","lastModified":1619280154000},{"path":"\/eduardo_blanco_bielsa_session11_task_newsstand\/src\/uo\/mp\/newsstand\/service\/serializers","parentWorkspace":"C:\/Users\/blanc\/OneDrive\/Documentos\/1er Curso\/2º Cuatrimestre\/MP\/Lab\/Sesión 11\/ws11","name":"PublicationSerializer.java","lastModified":1585492126000},{"path":"\/lab12_exam_marker_initial\/src\/uo\/mp\/lab12\/parsers","parentWorkspace":"C:\/Users\/blanc\/OneDrive\/Documentos\/1er Curso\/2º Cuatrimestre\/MP\/Lab\/Sesión 11\/ws11","name":"StudentParser.java","lastModified":1619277484000},{"path":"\/eduardo_blanco_bielsa_session11_task_newsstand\/src\/uo\/mp\/newsstand\/domain","parentWorkspace":"C:\/Users\/blanc\/OneDrive\/Documentos\/1er Curso\/2º Cuatrimestre\/MP\/Lab\/Sesión 11\/ws11","name":"Order.java","lastModified":1616835838000},{"path":"\/eduardo_blanco_bielsa_session11_task_newsstand\/src\/uo\/mp\/newsstand\/service\/serializers","parentWorkspace":"C:\/Users\/blanc\/OneDrive\/Documentos\/1er Curso\/2º Cuatrimestre\/MP\/Lab\/Sesión 11\/ws11","name":"OrderSerializer.java","lastModified":1618314506000},{"path":"\/lab12_exam_marker_initial\/src\/uo\/mp\/lab12\/questions","parentWorkspace":"C:\/Users\/blanc\/OneDrive\/Documentos\/1er Curso\/2º Cuatrimestre\/MP\/Lab\/Sesión 11\/ws11","name":"Question.java","lastModified":1632763865466},{"path":"\/eduardo_blanco_bielsa_session11_task_newsstand\/src\/uo\/mp\/newsstand\/domain","parentWorkspace":"C:\/Users\/blanc\/OneDrive\/Documentos\/1er Curso\/2º Cuatrimestre\/MP\/Lab\/Sesión 11\/ws11","name":"Newspaper.java","lastModified":1618649080000},{"path":"\/eduardo_blanco_bielsa_session11_task_newsstand\/src\/uo\/mp\/newsstand\/domain","parentWorkspace":"C:\/Users\/blanc\/OneDrive\/Documentos\/1er Curso\/2º Cuatrimestre\/MP\/Lab\/Sesión 11\/ws11","name":"Publication.java","lastModified":1619186400000},{"path":"\/lab12_exam_marker_initial\/src\/uo\/mp\/lab12\/questions","parentWorkspace":"C:\/Users\/blanc\/OneDrive\/Documentos\/1er Curso\/2º Cuatrimestre\/MP\/Lab\/Sesión 11\/ws11","name":"Gap.java","lastModified":1632763865466},{"path":"\/lab12_exam_marker_initial\/src\/uo\/mp\/lab12\/marker","parentWorkspace":"C:\/Users\/blanc\/OneDrive\/Documentos\/1er Curso\/2º Cuatrimestre\/MP\/Lab\/Sesión 11\/ws11","name":"ExamMarker.java","lastModified":1619281072000},{"path":"\/lab12_exam_marker_initial\/src\/uo\/mp\/lab12\/studentexams","parentWorkspace":"C:\/Users\/blanc\/OneDrive\/Documentos\/1er Curso\/2º Cuatrimestre\/MP\/Lab\/Sesión 11\/ws11","name":"StudentExam.java","lastModified":1619276654000},{"path":"\/eduardo_blanco_bielsa_session11_task_newsstand\/src\/uo\/mp\/newsstand\/service\/parsers","parentWorkspace":"C:\/Users\/blanc\/OneDrive\/Documentos\/1er Curso\/2º Cuatrimestre\/MP\/Lab\/Sesión 11\/ws11","name":"PublicationParser.java","lastModified":1618308960000}]}